{
  "file": "c1-p0-n1-l4-a0.hbt",
  "runs": [
    {
      "start": "1334615024900",
      "end": "1334637514200",
      "memory": [
        {
          "allocated": {
            "rss": 43433984,
            "heapTotal": 11689984,
            "heapUsed": 8367216,
            "external": 2373206,
            "arrayBuffers": 467914
          },
          "delta": "1334615180900"
        },
        {
          "allocated": {
            "rss": 46006272,
            "heapTotal": 17195008,
            "heapUsed": 9731528,
            "external": 2372506,
            "arrayBuffers": 467914
          },
          "delta": "1334632697100"
        },
        {
          "allocated": {
            "rss": 46120960,
            "heapTotal": 17195008,
            "heapUsed": 9845056,
            "external": 2372506,
            "arrayBuffers": 467914
          },
          "delta": "1334634430000"
        },
        {
          "allocated": {
            "rss": 46129152,
            "heapTotal": 17195008,
            "heapUsed": 9849600,
            "external": 2372506,
            "arrayBuffers": 467914
          },
          "delta": "1334634699600"
        },
        {
          "allocated": {
            "rss": 46133248,
            "heapTotal": 17195008,
            "heapUsed": 9851424,
            "external": 2372506,
            "arrayBuffers": 467914
          },
          "delta": "1334634806000"
        },
        {
          "allocated": {
            "rss": 46149632,
            "heapTotal": 17195008,
            "heapUsed": 9858120,
            "external": 2372506,
            "arrayBuffers": 467914
          },
          "delta": "1334635397600"
        },
        {
          "allocated": {
            "rss": 46149632,
            "heapTotal": 17195008,
            "heapUsed": 9859904,
            "external": 2372506,
            "arrayBuffers": 467914
          },
          "delta": "1334635505700"
        },
        {
          "allocated": {
            "rss": 46153728,
            "heapTotal": 17195008,
            "heapUsed": 9861488,
            "external": 2372506,
            "arrayBuffers": 467914
          },
          "delta": "1334635616600"
        },
        {
          "allocated": {
            "rss": 46178304,
            "heapTotal": 17195008,
            "heapUsed": 10101144,
            "external": 2372506,
            "arrayBuffers": 467914
          },
          "delta": "1334637508300"
        }
      ]
    },
    {
      "start": "1334792785600",
      "end": "1334814528700",
      "memory": [
        {
          "allocated": {
            "rss": 43515904,
            "heapTotal": 11427840,
            "heapUsed": 8433152,
            "external": 2377502,
            "arrayBuffers": 465430
          },
          "delta": "1334792936300"
        },
        {
          "allocated": {
            "rss": 45940736,
            "heapTotal": 17457152,
            "heapUsed": 9868776,
            "external": 2370022,
            "arrayBuffers": 465430
          },
          "delta": "1334809846700"
        },
        {
          "allocated": {
            "rss": 46047232,
            "heapTotal": 17457152,
            "heapUsed": 9895088,
            "external": 2370022,
            "arrayBuffers": 465430
          },
          "delta": "1334811577600"
        },
        {
          "allocated": {
            "rss": 46055424,
            "heapTotal": 17457152,
            "heapUsed": 9899632,
            "external": 2370022,
            "arrayBuffers": 465430
          },
          "delta": "1334811855300"
        },
        {
          "allocated": {
            "rss": 46059520,
            "heapTotal": 17457152,
            "heapUsed": 9901456,
            "external": 2370022,
            "arrayBuffers": 465430
          },
          "delta": "1334811951100"
        },
        {
          "allocated": {
            "rss": 46071808,
            "heapTotal": 17457152,
            "heapUsed": 9908152,
            "external": 2370022,
            "arrayBuffers": 465430
          },
          "delta": "1334812549600"
        },
        {
          "allocated": {
            "rss": 46075904,
            "heapTotal": 17457152,
            "heapUsed": 9909936,
            "external": 2370022,
            "arrayBuffers": 465430
          },
          "delta": "1334812662400"
        },
        {
          "allocated": {
            "rss": 46075904,
            "heapTotal": 17457152,
            "heapUsed": 10160536,
            "external": 2370022,
            "arrayBuffers": 465430
          },
          "delta": "1334812779800"
        },
        {
          "allocated": {
            "rss": 46104576,
            "heapTotal": 17457152,
            "heapUsed": 10173608,
            "external": 2370022,
            "arrayBuffers": 465430
          },
          "delta": "1334814522200"
        }
      ]
    },
    {
      "start": "1334972156100",
      "end": "1334994425200",
      "memory": [
        {
          "allocated": {
            "rss": 43741184,
            "heapTotal": 11427840,
            "heapUsed": 8502880,
            "external": 2377502,
            "arrayBuffers": 465430
          },
          "delta": "1334972310800"
        },
        {
          "allocated": {
            "rss": 45953024,
            "heapTotal": 16932864,
            "heapUsed": 9933216,
            "external": 2370022,
            "arrayBuffers": 465430
          },
          "delta": "1334989706500"
        },
        {
          "allocated": {
            "rss": 46063616,
            "heapTotal": 16932864,
            "heapUsed": 9959528,
            "external": 2370022,
            "arrayBuffers": 465430
          },
          "delta": "1334991448700"
        },
        {
          "allocated": {
            "rss": 46071808,
            "heapTotal": 16932864,
            "heapUsed": 9964072,
            "external": 2370022,
            "arrayBuffers": 465430
          },
          "delta": "1334991729000"
        },
        {
          "allocated": {
            "rss": 46075904,
            "heapTotal": 16932864,
            "heapUsed": 9965896,
            "external": 2370022,
            "arrayBuffers": 465430
          },
          "delta": "1334991829300"
        },
        {
          "allocated": {
            "rss": 46092288,
            "heapTotal": 16932864,
            "heapUsed": 9972592,
            "external": 2370022,
            "arrayBuffers": 465430
          },
          "delta": "1334992429400"
        },
        {
          "allocated": {
            "rss": 46092288,
            "heapTotal": 16932864,
            "heapUsed": 9974376,
            "external": 2370022,
            "arrayBuffers": 465430
          },
          "delta": "1334992540300"
        },
        {
          "allocated": {
            "rss": 46096384,
            "heapTotal": 16932864,
            "heapUsed": 9975960,
            "external": 2370022,
            "arrayBuffers": 465430
          },
          "delta": "1334992654500"
        },
        {
          "allocated": {
            "rss": 46125056,
            "heapTotal": 16932864,
            "heapUsed": 9989032,
            "external": 2370022,
            "arrayBuffers": 465430
          },
          "delta": "1334994419200"
        }
      ]
    },
    {
      "start": "1335152139300",
      "end": "1335175311200",
      "memory": [
        {
          "allocated": {
            "rss": 43720704,
            "heapTotal": 11427840,
            "heapUsed": 8333608,
            "external": 2344052,
            "arrayBuffers": 438760
          },
          "delta": "1335152305400"
        },
        {
          "allocated": {
            "rss": 46178304,
            "heapTotal": 17195008,
            "heapUsed": 9950592,
            "external": 2343352,
            "arrayBuffers": 438760
          },
          "delta": "1335170628500"
        },
        {
          "allocated": {
            "rss": 46297088,
            "heapTotal": 17195008,
            "heapUsed": 9976904,
            "external": 2343352,
            "arrayBuffers": 438760
          },
          "delta": "1335172379000"
        },
        {
          "allocated": {
            "rss": 46305280,
            "heapTotal": 17195008,
            "heapUsed": 9981448,
            "external": 2343352,
            "arrayBuffers": 438760
          },
          "delta": "1335172655100"
        },
        {
          "allocated": {
            "rss": 46305280,
            "heapTotal": 17195008,
            "heapUsed": 9983272,
            "external": 2343352,
            "arrayBuffers": 438760
          },
          "delta": "1335172747400"
        },
        {
          "allocated": {
            "rss": 46321664,
            "heapTotal": 17195008,
            "heapUsed": 9989968,
            "external": 2343352,
            "arrayBuffers": 438760
          },
          "delta": "1335173348800"
        },
        {
          "allocated": {
            "rss": 46325760,
            "heapTotal": 17195008,
            "heapUsed": 9991752,
            "external": 2343352,
            "arrayBuffers": 438760
          },
          "delta": "1335173461300"
        },
        {
          "allocated": {
            "rss": 46329856,
            "heapTotal": 17195008,
            "heapUsed": 9993336,
            "external": 2343352,
            "arrayBuffers": 438760
          },
          "delta": "1335173573700"
        },
        {
          "allocated": {
            "rss": 46354432,
            "heapTotal": 17195008,
            "heapUsed": 10006408,
            "external": 2343352,
            "arrayBuffers": 438760
          },
          "delta": "1335175304600"
        }
      ]
    },
    {
      "start": "1335334932700",
      "end": "1335357225500",
      "memory": [
        {
          "allocated": {
            "rss": 43397120,
            "heapTotal": 11427840,
            "heapUsed": 8449744,
            "external": 2338103,
            "arrayBuffers": 426031
          },
          "delta": "1335335088000"
        },
        {
          "allocated": {
            "rss": 45768704,
            "heapTotal": 17195008,
            "heapUsed": 9872792,
            "external": 2330623,
            "arrayBuffers": 426031
          },
          "delta": "1335352543300"
        },
        {
          "allocated": {
            "rss": 45879296,
            "heapTotal": 17195008,
            "heapUsed": 9899104,
            "external": 2330623,
            "arrayBuffers": 426031
          },
          "delta": "1335354259400"
        },
        {
          "allocated": {
            "rss": 45887488,
            "heapTotal": 17195008,
            "heapUsed": 9903648,
            "external": 2330623,
            "arrayBuffers": 426031
          },
          "delta": "1335354537600"
        },
        {
          "allocated": {
            "rss": 45887488,
            "heapTotal": 17195008,
            "heapUsed": 9905472,
            "external": 2330623,
            "arrayBuffers": 426031
          },
          "delta": "1335354631600"
        },
        {
          "allocated": {
            "rss": 45903872,
            "heapTotal": 17195008,
            "heapUsed": 9912168,
            "external": 2330623,
            "arrayBuffers": 426031
          },
          "delta": "1335355220800"
        },
        {
          "allocated": {
            "rss": 45907968,
            "heapTotal": 17195008,
            "heapUsed": 9913952,
            "external": 2330623,
            "arrayBuffers": 426031
          },
          "delta": "1335355335800"
        },
        {
          "allocated": {
            "rss": 45907968,
            "heapTotal": 17195008,
            "heapUsed": 9915536,
            "external": 2330623,
            "arrayBuffers": 426031
          },
          "delta": "1335355443700"
        },
        {
          "allocated": {
            "rss": 45936640,
            "heapTotal": 17195008,
            "heapUsed": 9928608,
            "external": 2330623,
            "arrayBuffers": 426031
          },
          "delta": "1335357219700"
        }
      ]
    },
    {
      "start": "1335513056100",
      "end": "1335534819200",
      "memory": [
        {
          "allocated": {
            "rss": 43315200,
            "heapTotal": 11427840,
            "heapUsed": 8297520,
            "external": 2331323,
            "arrayBuffers": 426031
          },
          "delta": "1335513204800"
        },
        {
          "allocated": {
            "rss": 45641728,
            "heapTotal": 17195008,
            "heapUsed": 9970728,
            "external": 2330623,
            "arrayBuffers": 426031
          },
          "delta": "1335530219700"
        },
        {
          "allocated": {
            "rss": 45772800,
            "heapTotal": 17195008,
            "heapUsed": 9997040,
            "external": 2330623,
            "arrayBuffers": 426031
          },
          "delta": "1335531925900"
        },
        {
          "allocated": {
            "rss": 45780992,
            "heapTotal": 17195008,
            "heapUsed": 10001584,
            "external": 2330623,
            "arrayBuffers": 426031
          },
          "delta": "1335532195800"
        },
        {
          "allocated": {
            "rss": 45785088,
            "heapTotal": 17195008,
            "heapUsed": 10003408,
            "external": 2330623,
            "arrayBuffers": 426031
          },
          "delta": "1335532292800"
        },
        {
          "allocated": {
            "rss": 45797376,
            "heapTotal": 17195008,
            "heapUsed": 10010104,
            "external": 2330623,
            "arrayBuffers": 426031
          },
          "delta": "1335532876900"
        },
        {
          "allocated": {
            "rss": 45801472,
            "heapTotal": 17195008,
            "heapUsed": 10011888,
            "external": 2330623,
            "arrayBuffers": 426031
          },
          "delta": "1335532987500"
        },
        {
          "allocated": {
            "rss": 45805568,
            "heapTotal": 17195008,
            "heapUsed": 10013472,
            "external": 2330623,
            "arrayBuffers": 426031
          },
          "delta": "1335533096800"
        },
        {
          "allocated": {
            "rss": 45830144,
            "heapTotal": 17195008,
            "heapUsed": 10026544,
            "external": 2330623,
            "arrayBuffers": 426031
          },
          "delta": "1335534812400"
        }
      ]
    },
    {
      "start": "1335688977600",
      "end": "1335711445500",
      "memory": [
        {
          "allocated": {
            "rss": 43282432,
            "heapTotal": 11427840,
            "heapUsed": 8308600,
            "external": 2331323,
            "arrayBuffers": 426031
          },
          "delta": "1335689124800"
        },
        {
          "allocated": {
            "rss": 45568000,
            "heapTotal": 17457152,
            "heapUsed": 9961112,
            "external": 2330623,
            "arrayBuffers": 426031
          },
          "delta": "1335706468100"
        },
        {
          "allocated": {
            "rss": 45707264,
            "heapTotal": 17457152,
            "heapUsed": 9987424,
            "external": 2330623,
            "arrayBuffers": 426031
          },
          "delta": "1335708363100"
        },
        {
          "allocated": {
            "rss": 45719552,
            "heapTotal": 17457152,
            "heapUsed": 9991968,
            "external": 2330623,
            "arrayBuffers": 426031
          },
          "delta": "1335708640400"
        },
        {
          "allocated": {
            "rss": 45723648,
            "heapTotal": 17457152,
            "heapUsed": 9993792,
            "external": 2330623,
            "arrayBuffers": 426031
          },
          "delta": "1335708799000"
        },
        {
          "allocated": {
            "rss": 45740032,
            "heapTotal": 17457152,
            "heapUsed": 10000488,
            "external": 2330623,
            "arrayBuffers": 426031
          },
          "delta": "1335709402700"
        },
        {
          "allocated": {
            "rss": 45740032,
            "heapTotal": 17457152,
            "heapUsed": 10002272,
            "external": 2330623,
            "arrayBuffers": 426031
          },
          "delta": "1335709512300"
        },
        {
          "allocated": {
            "rss": 45744128,
            "heapTotal": 17457152,
            "heapUsed": 10003856,
            "external": 2330623,
            "arrayBuffers": 426031
          },
          "delta": "1335709626500"
        },
        {
          "allocated": {
            "rss": 45772800,
            "heapTotal": 17457152,
            "heapUsed": 10016928,
            "external": 2330623,
            "arrayBuffers": 426031
          },
          "delta": "1335711438000"
        }
      ]
    },
    {
      "start": "1335865199700",
      "end": "1335887369800",
      "memory": [
        {
          "allocated": {
            "rss": 43667456,
            "heapTotal": 11427840,
            "heapUsed": 8544416,
            "external": 2370722,
            "arrayBuffers": 465430
          },
          "delta": "1335865356200"
        },
        {
          "allocated": {
            "rss": 46108672,
            "heapTotal": 17195008,
            "heapUsed": 9837992,
            "external": 2370022,
            "arrayBuffers": 465430
          },
          "delta": "1335882693100"
        },
        {
          "allocated": {
            "rss": 46211072,
            "heapTotal": 17195008,
            "heapUsed": 9976968,
            "external": 2370022,
            "arrayBuffers": 465430
          },
          "delta": "1335884398700"
        },
        {
          "allocated": {
            "rss": 46219264,
            "heapTotal": 17195008,
            "heapUsed": 9981512,
            "external": 2370022,
            "arrayBuffers": 465430
          },
          "delta": "1335884668000"
        },
        {
          "allocated": {
            "rss": 46219264,
            "heapTotal": 17195008,
            "heapUsed": 9983336,
            "external": 2370022,
            "arrayBuffers": 465430
          },
          "delta": "1335884759100"
        },
        {
          "allocated": {
            "rss": 46235648,
            "heapTotal": 17195008,
            "heapUsed": 9990056,
            "external": 2370022,
            "arrayBuffers": 465430
          },
          "delta": "1335885347700"
        },
        {
          "allocated": {
            "rss": 46239744,
            "heapTotal": 17195008,
            "heapUsed": 9991840,
            "external": 2370022,
            "arrayBuffers": 465430
          },
          "delta": "1335885459400"
        },
        {
          "allocated": {
            "rss": 46243840,
            "heapTotal": 17195008,
            "heapUsed": 9993424,
            "external": 2370022,
            "arrayBuffers": 465430
          },
          "delta": "1335885570100"
        },
        {
          "allocated": {
            "rss": 46268416,
            "heapTotal": 17195008,
            "heapUsed": 10006496,
            "external": 2370022,
            "arrayBuffers": 465430
          },
          "delta": "1335887363400"
        }
      ]
    },
    {
      "start": "1336041942600",
      "end": "1336063941300",
      "memory": [
        {
          "allocated": {
            "rss": 43458560,
            "heapTotal": 11427840,
            "heapUsed": 8470600,
            "external": 2377502,
            "arrayBuffers": 465430
          },
          "delta": "1336042088200"
        },
        {
          "allocated": {
            "rss": 45793280,
            "heapTotal": 17195008,
            "heapUsed": 9853976,
            "external": 2370022,
            "arrayBuffers": 465430
          },
          "delta": "1336059228300"
        },
        {
          "allocated": {
            "rss": 45912064,
            "heapTotal": 17195008,
            "heapUsed": 9880288,
            "external": 2370022,
            "arrayBuffers": 465430
          },
          "delta": "1336060942800"
        },
        {
          "allocated": {
            "rss": 45920256,
            "heapTotal": 17195008,
            "heapUsed": 9884832,
            "external": 2370022,
            "arrayBuffers": 465430
          },
          "delta": "1336061213300"
        },
        {
          "allocated": {
            "rss": 45920256,
            "heapTotal": 17195008,
            "heapUsed": 9886656,
            "external": 2370022,
            "arrayBuffers": 465430
          },
          "delta": "1336061314500"
        },
        {
          "allocated": {
            "rss": 45936640,
            "heapTotal": 17195008,
            "heapUsed": 9971120,
            "external": 2370022,
            "arrayBuffers": 465430
          },
          "delta": "1336061923700"
        },
        {
          "allocated": {
            "rss": 45940736,
            "heapTotal": 17195008,
            "heapUsed": 9972904,
            "external": 2370022,
            "arrayBuffers": 465430
          },
          "delta": "1336062034800"
        },
        {
          "allocated": {
            "rss": 45940736,
            "heapTotal": 17195008,
            "heapUsed": 9974488,
            "external": 2370022,
            "arrayBuffers": 465430
          },
          "delta": "1336062142100"
        },
        {
          "allocated": {
            "rss": 45969408,
            "heapTotal": 17195008,
            "heapUsed": 9987560,
            "external": 2370022,
            "arrayBuffers": 465430
          },
          "delta": "1336063935900"
        }
      ]
    },
    {
      "start": "1336221560500",
      "end": "1336243598600",
      "memory": [
        {
          "allocated": {
            "rss": 43536384,
            "heapTotal": 11427840,
            "heapUsed": 8580008,
            "external": 2373206,
            "arrayBuffers": 467914
          },
          "delta": "1336221711700"
        },
        {
          "allocated": {
            "rss": 46047232,
            "heapTotal": 17195008,
            "heapUsed": 9986760,
            "external": 2372506,
            "arrayBuffers": 467914
          },
          "delta": "1336238923600"
        },
        {
          "allocated": {
            "rss": 46153728,
            "heapTotal": 17195008,
            "heapUsed": 10013072,
            "external": 2372506,
            "arrayBuffers": 467914
          },
          "delta": "1336240662400"
        },
        {
          "allocated": {
            "rss": 46161920,
            "heapTotal": 17195008,
            "heapUsed": 10017616,
            "external": 2372506,
            "arrayBuffers": 467914
          },
          "delta": "1336240941600"
        },
        {
          "allocated": {
            "rss": 46166016,
            "heapTotal": 17195008,
            "heapUsed": 10019440,
            "external": 2372506,
            "arrayBuffers": 467914
          },
          "delta": "1336241037100"
        },
        {
          "allocated": {
            "rss": 46178304,
            "heapTotal": 17195008,
            "heapUsed": 10026136,
            "external": 2372506,
            "arrayBuffers": 467914
          },
          "delta": "1336241628900"
        },
        {
          "allocated": {
            "rss": 46182400,
            "heapTotal": 17195008,
            "heapUsed": 10027944,
            "external": 2372506,
            "arrayBuffers": 467914
          },
          "delta": "1336241745700"
        },
        {
          "allocated": {
            "rss": 46186496,
            "heapTotal": 17195008,
            "heapUsed": 10029528,
            "external": 2372506,
            "arrayBuffers": 467914
          },
          "delta": "1336241874500"
        },
        {
          "allocated": {
            "rss": 46215168,
            "heapTotal": 17195008,
            "heapUsed": 10042600,
            "external": 2372506,
            "arrayBuffers": 467914
          },
          "delta": "1336243591800"
        }
      ]
    },
    {
      "start": "1336401454700",
      "end": "1336423460700",
      "memory": [
        {
          "allocated": {
            "rss": 43413504,
            "heapTotal": 11427840,
            "heapUsed": 8486472,
            "external": 2377502,
            "arrayBuffers": 465430
          },
          "delta": "1336401605900"
        },
        {
          "allocated": {
            "rss": 45875200,
            "heapTotal": 17195008,
            "heapUsed": 9904656,
            "external": 2370022,
            "arrayBuffers": 465430
          },
          "delta": "1336418743400"
        },
        {
          "allocated": {
            "rss": 45981696,
            "heapTotal": 17195008,
            "heapUsed": 9930968,
            "external": 2370022,
            "arrayBuffers": 465430
          },
          "delta": "1336420457800"
        },
        {
          "allocated": {
            "rss": 45993984,
            "heapTotal": 17195008,
            "heapUsed": 9935512,
            "external": 2370022,
            "arrayBuffers": 465430
          },
          "delta": "1336420733500"
        },
        {
          "allocated": {
            "rss": 45993984,
            "heapTotal": 17195008,
            "heapUsed": 9937336,
            "external": 2370022,
            "arrayBuffers": 465430
          },
          "delta": "1336420830400"
        },
        {
          "allocated": {
            "rss": 46010368,
            "heapTotal": 17195008,
            "heapUsed": 9944032,
            "external": 2370022,
            "arrayBuffers": 465430
          },
          "delta": "1336421420500"
        },
        {
          "allocated": {
            "rss": 46010368,
            "heapTotal": 17195008,
            "heapUsed": 9945816,
            "external": 2370022,
            "arrayBuffers": 465430
          },
          "delta": "1336421530000"
        },
        {
          "allocated": {
            "rss": 46014464,
            "heapTotal": 17195008,
            "heapUsed": 9947400,
            "external": 2370022,
            "arrayBuffers": 465430
          },
          "delta": "1336421641200"
        },
        {
          "allocated": {
            "rss": 46043136,
            "heapTotal": 17195008,
            "heapUsed": 9960472,
            "external": 2370022,
            "arrayBuffers": 465430
          },
          "delta": "1336423454700"
        }
      ]
    },
    {
      "start": "1336578622000",
      "end": "1336600629500",
      "memory": [
        {
          "allocated": {
            "rss": 43966464,
            "heapTotal": 11427840,
            "heapUsed": 8463960,
            "external": 2370722,
            "arrayBuffers": 465430
          },
          "delta": "1336578776100"
        },
        {
          "allocated": {
            "rss": 46227456,
            "heapTotal": 17457152,
            "heapUsed": 9843472,
            "external": 2370022,
            "arrayBuffers": 465430
          },
          "delta": "1336595956500"
        },
        {
          "allocated": {
            "rss": 46350336,
            "heapTotal": 17457152,
            "heapUsed": 9869784,
            "external": 2370022,
            "arrayBuffers": 465430
          },
          "delta": "1336597683600"
        },
        {
          "allocated": {
            "rss": 46354432,
            "heapTotal": 17457152,
            "heapUsed": 10089376,
            "external": 2370022,
            "arrayBuffers": 465430
          },
          "delta": "1336597958800"
        },
        {
          "allocated": {
            "rss": 46358528,
            "heapTotal": 17457152,
            "heapUsed": 10091200,
            "external": 2370022,
            "arrayBuffers": 465430
          },
          "delta": "1336598052600"
        },
        {
          "allocated": {
            "rss": 46370816,
            "heapTotal": 17457152,
            "heapUsed": 10097896,
            "external": 2370022,
            "arrayBuffers": 465430
          },
          "delta": "1336598634200"
        },
        {
          "allocated": {
            "rss": 46374912,
            "heapTotal": 17457152,
            "heapUsed": 10099680,
            "external": 2370022,
            "arrayBuffers": 465430
          },
          "delta": "1336598744200"
        },
        {
          "allocated": {
            "rss": 46379008,
            "heapTotal": 17457152,
            "heapUsed": 10101264,
            "external": 2370022,
            "arrayBuffers": 465430
          },
          "delta": "1336598865900"
        },
        {
          "allocated": {
            "rss": 46407680,
            "heapTotal": 17457152,
            "heapUsed": 10114336,
            "external": 2370022,
            "arrayBuffers": 465430
          },
          "delta": "1336600623200"
        }
      ]
    },
    {
      "start": "1336755281900",
      "end": "1336777118000",
      "memory": [
        {
          "allocated": {
            "rss": 43524096,
            "heapTotal": 11689984,
            "heapUsed": 8402272,
            "external": 2331323,
            "arrayBuffers": 426031
          },
          "delta": "1336755438000"
        },
        {
          "allocated": {
            "rss": 45875200,
            "heapTotal": 17457152,
            "heapUsed": 9794776,
            "external": 2330623,
            "arrayBuffers": 426031
          },
          "delta": "1336772477500"
        },
        {
          "allocated": {
            "rss": 45989888,
            "heapTotal": 17457152,
            "heapUsed": 9981352,
            "external": 2330623,
            "arrayBuffers": 426031
          },
          "delta": "1336774169400"
        },
        {
          "allocated": {
            "rss": 45998080,
            "heapTotal": 17457152,
            "heapUsed": 9985896,
            "external": 2330623,
            "arrayBuffers": 426031
          },
          "delta": "1336774443100"
        },
        {
          "allocated": {
            "rss": 45998080,
            "heapTotal": 17457152,
            "heapUsed": 9987720,
            "external": 2330623,
            "arrayBuffers": 426031
          },
          "delta": "1336774535200"
        },
        {
          "allocated": {
            "rss": 46018560,
            "heapTotal": 17457152,
            "heapUsed": 9994416,
            "external": 2330623,
            "arrayBuffers": 426031
          },
          "delta": "1336775124300"
        },
        {
          "allocated": {
            "rss": 46022656,
            "heapTotal": 17457152,
            "heapUsed": 9996200,
            "external": 2330623,
            "arrayBuffers": 426031
          },
          "delta": "1336775233800"
        },
        {
          "allocated": {
            "rss": 46022656,
            "heapTotal": 17457152,
            "heapUsed": 9997784,
            "external": 2330623,
            "arrayBuffers": 426031
          },
          "delta": "1336775345200"
        },
        {
          "allocated": {
            "rss": 46051328,
            "heapTotal": 17457152,
            "heapUsed": 10010856,
            "external": 2330623,
            "arrayBuffers": 426031
          },
          "delta": "1336777112200"
        }
      ]
    },
    {
      "start": "1336931232900",
      "end": "1336953274800",
      "memory": [
        {
          "allocated": {
            "rss": 43270144,
            "heapTotal": 11689984,
            "heapUsed": 8404288,
            "external": 2370722,
            "arrayBuffers": 465430
          },
          "delta": "1336931387100"
        },
        {
          "allocated": {
            "rss": 45543424,
            "heapTotal": 16932864,
            "heapUsed": 9845872,
            "external": 2370022,
            "arrayBuffers": 465430
          },
          "delta": "1336948399600"
        },
        {
          "allocated": {
            "rss": 45699072,
            "heapTotal": 16932864,
            "heapUsed": 9872184,
            "external": 2370022,
            "arrayBuffers": 465430
          },
          "delta": "1336950355400"
        },
        {
          "allocated": {
            "rss": 45707264,
            "heapTotal": 16932864,
            "heapUsed": 9876728,
            "external": 2370022,
            "arrayBuffers": 465430
          },
          "delta": "1336950633700"
        },
        {
          "allocated": {
            "rss": 45711360,
            "heapTotal": 16932864,
            "heapUsed": 9878552,
            "external": 2370022,
            "arrayBuffers": 465430
          },
          "delta": "1336950729400"
        },
        {
          "allocated": {
            "rss": 45744128,
            "heapTotal": 17195008,
            "heapUsed": 10145856,
            "external": 2370022,
            "arrayBuffers": 465430
          },
          "delta": "1336951356600"
        },
        {
          "allocated": {
            "rss": 45748224,
            "heapTotal": 17195008,
            "heapUsed": 10147640,
            "external": 2370022,
            "arrayBuffers": 465430
          },
          "delta": "1336951467700"
        },
        {
          "allocated": {
            "rss": 45752320,
            "heapTotal": 17195008,
            "heapUsed": 10149224,
            "external": 2370022,
            "arrayBuffers": 465430
          },
          "delta": "1336951578800"
        },
        {
          "allocated": {
            "rss": 45776896,
            "heapTotal": 17195008,
            "heapUsed": 10162296,
            "external": 2370022,
            "arrayBuffers": 465430
          },
          "delta": "1336953269200"
        }
      ]
    },
    {
      "start": "1337109335300",
      "end": "1337131990100",
      "memory": [
        {
          "allocated": {
            "rss": 43315200,
            "heapTotal": 11427840,
            "heapUsed": 8382600,
            "external": 2338103,
            "arrayBuffers": 426031
          },
          "delta": "1337109490800"
        },
        {
          "allocated": {
            "rss": 45772800,
            "heapTotal": 16932864,
            "heapUsed": 9944704,
            "external": 2330623,
            "arrayBuffers": 426031
          },
          "delta": "1337127103800"
        },
        {
          "allocated": {
            "rss": 45879296,
            "heapTotal": 16932864,
            "heapUsed": 9971016,
            "external": 2330623,
            "arrayBuffers": 426031
          },
          "delta": "1337128851200"
        },
        {
          "allocated": {
            "rss": 45887488,
            "heapTotal": 16932864,
            "heapUsed": 9975560,
            "external": 2330623,
            "arrayBuffers": 426031
          },
          "delta": "1337129127300"
        },
        {
          "allocated": {
            "rss": 45887488,
            "heapTotal": 16932864,
            "heapUsed": 9977384,
            "external": 2330623,
            "arrayBuffers": 426031
          },
          "delta": "1337129222500"
        },
        {
          "allocated": {
            "rss": 45903872,
            "heapTotal": 16932864,
            "heapUsed": 9984080,
            "external": 2330623,
            "arrayBuffers": 426031
          },
          "delta": "1337129825300"
        },
        {
          "allocated": {
            "rss": 45907968,
            "heapTotal": 16932864,
            "heapUsed": 9985864,
            "external": 2330623,
            "arrayBuffers": 426031
          },
          "delta": "1337129939800"
        },
        {
          "allocated": {
            "rss": 45907968,
            "heapTotal": 16932864,
            "heapUsed": 9987448,
            "external": 2330623,
            "arrayBuffers": 426031
          },
          "delta": "1337130051400"
        },
        {
          "allocated": {
            "rss": 45936640,
            "heapTotal": 16932864,
            "heapUsed": 10000520,
            "external": 2330623,
            "arrayBuffers": 426031
          },
          "delta": "1337131980100"
        }
      ]
    },
    {
      "start": "1337292126400",
      "end": "1337313871000",
      "memory": [
        {
          "allocated": {
            "rss": 43761664,
            "heapTotal": 11427840,
            "heapUsed": 8521032,
            "external": 2379986,
            "arrayBuffers": 467914
          },
          "delta": "1337292277300"
        },
        {
          "allocated": {
            "rss": 46075904,
            "heapTotal": 17195008,
            "heapUsed": 9896624,
            "external": 2372506,
            "arrayBuffers": 467914
          },
          "delta": "1337309315500"
        },
        {
          "allocated": {
            "rss": 46186496,
            "heapTotal": 17195008,
            "heapUsed": 9992864,
            "external": 2372506,
            "arrayBuffers": 467914
          },
          "delta": "1337311019100"
        },
        {
          "allocated": {
            "rss": 46194688,
            "heapTotal": 17195008,
            "heapUsed": 9997408,
            "external": 2372506,
            "arrayBuffers": 467914
          },
          "delta": "1337311286100"
        },
        {
          "allocated": {
            "rss": 46194688,
            "heapTotal": 17195008,
            "heapUsed": 9999232,
            "external": 2372506,
            "arrayBuffers": 467914
          },
          "delta": "1337311380200"
        },
        {
          "allocated": {
            "rss": 46211072,
            "heapTotal": 17195008,
            "heapUsed": 10005928,
            "external": 2372506,
            "arrayBuffers": 467914
          },
          "delta": "1337311963200"
        },
        {
          "allocated": {
            "rss": 46215168,
            "heapTotal": 17195008,
            "heapUsed": 10007712,
            "external": 2372506,
            "arrayBuffers": 467914
          },
          "delta": "1337312073300"
        },
        {
          "allocated": {
            "rss": 46215168,
            "heapTotal": 17195008,
            "heapUsed": 10009296,
            "external": 2372506,
            "arrayBuffers": 467914
          },
          "delta": "1337312179100"
        },
        {
          "allocated": {
            "rss": 46243840,
            "heapTotal": 17195008,
            "heapUsed": 10022368,
            "external": 2372506,
            "arrayBuffers": 467914
          },
          "delta": "1337313865000"
        }
      ]
    },
    {
      "start": "1337469339800",
      "end": "1337491387100",
      "memory": [
        {
          "allocated": {
            "rss": 43356160,
            "heapTotal": 11165696,
            "heapUsed": 8364576,
            "external": 2370722,
            "arrayBuffers": 465430
          },
          "delta": "1337469493200"
        },
        {
          "allocated": {
            "rss": 46112768,
            "heapTotal": 17457152,
            "heapUsed": 9911520,
            "external": 2370022,
            "arrayBuffers": 465430
          },
          "delta": "1337486701000"
        },
        {
          "allocated": {
            "rss": 46227456,
            "heapTotal": 17457152,
            "heapUsed": 9937832,
            "external": 2370022,
            "arrayBuffers": 465430
          },
          "delta": "1337488425200"
        },
        {
          "allocated": {
            "rss": 46235648,
            "heapTotal": 17457152,
            "heapUsed": 9942376,
            "external": 2370022,
            "arrayBuffers": 465430
          },
          "delta": "1337488699400"
        },
        {
          "allocated": {
            "rss": 46235648,
            "heapTotal": 17457152,
            "heapUsed": 9944200,
            "external": 2370022,
            "arrayBuffers": 465430
          },
          "delta": "1337488793700"
        },
        {
          "allocated": {
            "rss": 46260224,
            "heapTotal": 17457152,
            "heapUsed": 9950896,
            "external": 2370022,
            "arrayBuffers": 465430
          },
          "delta": "1337489384900"
        },
        {
          "allocated": {
            "rss": 46264320,
            "heapTotal": 17457152,
            "heapUsed": 9952680,
            "external": 2370022,
            "arrayBuffers": 465430
          },
          "delta": "1337489508500"
        },
        {
          "allocated": {
            "rss": 46268416,
            "heapTotal": 17457152,
            "heapUsed": 9954264,
            "external": 2370022,
            "arrayBuffers": 465430
          },
          "delta": "1337489619800"
        },
        {
          "allocated": {
            "rss": 46292992,
            "heapTotal": 17457152,
            "heapUsed": 9967352,
            "external": 2370022,
            "arrayBuffers": 465430
          },
          "delta": "1337491381300"
        }
      ]
    },
    {
      "start": "1337647076400",
      "end": "1337669502000",
      "memory": [
        {
          "allocated": {
            "rss": 43319296,
            "heapTotal": 11427840,
            "heapUsed": 8553784,
            "external": 2338103,
            "arrayBuffers": 426031
          },
          "delta": "1337647230000"
        },
        {
          "allocated": {
            "rss": 45895680,
            "heapTotal": 17195008,
            "heapUsed": 9847752,
            "external": 2330623,
            "arrayBuffers": 426031
          },
          "delta": "1337664810000"
        },
        {
          "allocated": {
            "rss": 46039040,
            "heapTotal": 17195008,
            "heapUsed": 10041208,
            "external": 2330623,
            "arrayBuffers": 426031
          },
          "delta": "1337666550000"
        },
        {
          "allocated": {
            "rss": 46051328,
            "heapTotal": 17195008,
            "heapUsed": 10045752,
            "external": 2330623,
            "arrayBuffers": 426031
          },
          "delta": "1337666828700"
        },
        {
          "allocated": {
            "rss": 46051328,
            "heapTotal": 17195008,
            "heapUsed": 10047576,
            "external": 2330623,
            "arrayBuffers": 426031
          },
          "delta": "1337666924900"
        },
        {
          "allocated": {
            "rss": 46067712,
            "heapTotal": 17195008,
            "heapUsed": 10054272,
            "external": 2330623,
            "arrayBuffers": 426031
          },
          "delta": "1337667521200"
        },
        {
          "allocated": {
            "rss": 46071808,
            "heapTotal": 17195008,
            "heapUsed": 10056056,
            "external": 2330623,
            "arrayBuffers": 426031
          },
          "delta": "1337667632700"
        },
        {
          "allocated": {
            "rss": 46071808,
            "heapTotal": 17195008,
            "heapUsed": 10057640,
            "external": 2330623,
            "arrayBuffers": 426031
          },
          "delta": "1337667744000"
        },
        {
          "allocated": {
            "rss": 46100480,
            "heapTotal": 17195008,
            "heapUsed": 10070712,
            "external": 2330623,
            "arrayBuffers": 426031
          },
          "delta": "1337669495900"
        }
      ]
    },
    {
      "start": "1337825318800",
      "end": "1337847132300",
      "memory": [
        {
          "allocated": {
            "rss": 43606016,
            "heapTotal": 11427840,
            "heapUsed": 8434680,
            "external": 2377446,
            "arrayBuffers": 465430
          },
          "delta": "1337825470900"
        },
        {
          "allocated": {
            "rss": 45846528,
            "heapTotal": 17195008,
            "heapUsed": 9998056,
            "external": 2370022,
            "arrayBuffers": 465430
          },
          "delta": "1337842522300"
        },
        {
          "allocated": {
            "rss": 45957120,
            "heapTotal": 17195008,
            "heapUsed": 10024368,
            "external": 2370022,
            "arrayBuffers": 465430
          },
          "delta": "1337844219700"
        },
        {
          "allocated": {
            "rss": 45965312,
            "heapTotal": 17195008,
            "heapUsed": 10028912,
            "external": 2370022,
            "arrayBuffers": 465430
          },
          "delta": "1337844496400"
        },
        {
          "allocated": {
            "rss": 45965312,
            "heapTotal": 17195008,
            "heapUsed": 10030736,
            "external": 2370022,
            "arrayBuffers": 465430
          },
          "delta": "1337844589500"
        },
        {
          "allocated": {
            "rss": 45981696,
            "heapTotal": 17195008,
            "heapUsed": 10037432,
            "external": 2370022,
            "arrayBuffers": 465430
          },
          "delta": "1337845179000"
        },
        {
          "allocated": {
            "rss": 45985792,
            "heapTotal": 17195008,
            "heapUsed": 10039216,
            "external": 2370022,
            "arrayBuffers": 465430
          },
          "delta": "1337845290300"
        },
        {
          "allocated": {
            "rss": 45989888,
            "heapTotal": 17195008,
            "heapUsed": 10040800,
            "external": 2370022,
            "arrayBuffers": 465430
          },
          "delta": "1337845402400"
        },
        {
          "allocated": {
            "rss": 46014464,
            "heapTotal": 17195008,
            "heapUsed": 10053872,
            "external": 2370022,
            "arrayBuffers": 465430
          },
          "delta": "1337847126600"
        }
      ]
    },
    {
      "start": "1338006673800",
      "end": "1338028533800",
      "memory": [
        {
          "allocated": {
            "rss": 43499520,
            "heapTotal": 11427840,
            "heapUsed": 8537632,
            "external": 2370722,
            "arrayBuffers": 465430
          },
          "delta": "1338006823100"
        },
        {
          "allocated": {
            "rss": 45903872,
            "heapTotal": 17195008,
            "heapUsed": 9830552,
            "external": 2370022,
            "arrayBuffers": 465430
          },
          "delta": "1338023825700"
        },
        {
          "allocated": {
            "rss": 46006272,
            "heapTotal": 17195008,
            "heapUsed": 9937296,
            "external": 2370022,
            "arrayBuffers": 465430
          },
          "delta": "1338025600800"
        },
        {
          "allocated": {
            "rss": 46014464,
            "heapTotal": 17195008,
            "heapUsed": 9941840,
            "external": 2370022,
            "arrayBuffers": 465430
          },
          "delta": "1338025877200"
        },
        {
          "allocated": {
            "rss": 46018560,
            "heapTotal": 17195008,
            "heapUsed": 9943664,
            "external": 2370022,
            "arrayBuffers": 465430
          },
          "delta": "1338025972300"
        },
        {
          "allocated": {
            "rss": 46034944,
            "heapTotal": 17195008,
            "heapUsed": 9950360,
            "external": 2370022,
            "arrayBuffers": 465430
          },
          "delta": "1338026585000"
        },
        {
          "allocated": {
            "rss": 46034944,
            "heapTotal": 17195008,
            "heapUsed": 9952144,
            "external": 2370022,
            "arrayBuffers": 465430
          },
          "delta": "1338026694100"
        },
        {
          "allocated": {
            "rss": 46039040,
            "heapTotal": 17195008,
            "heapUsed": 9953728,
            "external": 2370022,
            "arrayBuffers": 465430
          },
          "delta": "1338026804800"
        },
        {
          "allocated": {
            "rss": 46063616,
            "heapTotal": 17195008,
            "heapUsed": 10039976,
            "external": 2370022,
            "arrayBuffers": 465430
          },
          "delta": "1338028528100"
        }
      ]
    },
    {
      "start": "1338185526000",
      "end": "1338207938400",
      "memory": [
        {
          "allocated": {
            "rss": 43376640,
            "heapTotal": 11689984,
            "heapUsed": 8366768,
            "external": 2377390,
            "arrayBuffers": 465430
          },
          "delta": "1338185670900"
        },
        {
          "allocated": {
            "rss": 45793280,
            "heapTotal": 17195008,
            "heapUsed": 9790608,
            "external": 2370022,
            "arrayBuffers": 465430
          },
          "delta": "1338203049100"
        },
        {
          "allocated": {
            "rss": 45903872,
            "heapTotal": 17195008,
            "heapUsed": 9848888,
            "external": 2370022,
            "arrayBuffers": 465430
          },
          "delta": "1338204943900"
        },
        {
          "allocated": {
            "rss": 45912064,
            "heapTotal": 17195008,
            "heapUsed": 9917904,
            "external": 2370022,
            "arrayBuffers": 465430
          },
          "delta": "1338205222500"
        },
        {
          "allocated": {
            "rss": 45912064,
            "heapTotal": 17195008,
            "heapUsed": 9919728,
            "external": 2370022,
            "arrayBuffers": 465430
          },
          "delta": "1338205314400"
        },
        {
          "allocated": {
            "rss": 45928448,
            "heapTotal": 17195008,
            "heapUsed": 9926424,
            "external": 2370022,
            "arrayBuffers": 465430
          },
          "delta": "1338205913600"
        },
        {
          "allocated": {
            "rss": 45932544,
            "heapTotal": 17195008,
            "heapUsed": 9928208,
            "external": 2370022,
            "arrayBuffers": 465430
          },
          "delta": "1338206028900"
        },
        {
          "allocated": {
            "rss": 45936640,
            "heapTotal": 17195008,
            "heapUsed": 9929792,
            "external": 2370022,
            "arrayBuffers": 465430
          },
          "delta": "1338206146800"
        },
        {
          "allocated": {
            "rss": 45961216,
            "heapTotal": 17195008,
            "heapUsed": 9942864,
            "external": 2370022,
            "arrayBuffers": 465430
          },
          "delta": "1338207930100"
        }
      ]
    },
    {
      "start": "1338367511000",
      "end": "1338389750200",
      "memory": [
        {
          "allocated": {
            "rss": 43556864,
            "heapTotal": 11427840,
            "heapUsed": 8284400,
            "external": 2370722,
            "arrayBuffers": 465430
          },
          "delta": "1338367663300"
        },
        {
          "allocated": {
            "rss": 45998080,
            "heapTotal": 17457152,
            "heapUsed": 9953544,
            "external": 2370022,
            "arrayBuffers": 465430
          },
          "delta": "1338385086700"
        },
        {
          "allocated": {
            "rss": 46104576,
            "heapTotal": 17457152,
            "heapUsed": 9979856,
            "external": 2370022,
            "arrayBuffers": 465430
          },
          "delta": "1338386850500"
        },
        {
          "allocated": {
            "rss": 46112768,
            "heapTotal": 17457152,
            "heapUsed": 9984400,
            "external": 2370022,
            "arrayBuffers": 465430
          },
          "delta": "1338387128000"
        },
        {
          "allocated": {
            "rss": 46112768,
            "heapTotal": 17457152,
            "heapUsed": 9986224,
            "external": 2370022,
            "arrayBuffers": 465430
          },
          "delta": "1338387220200"
        },
        {
          "allocated": {
            "rss": 46129152,
            "heapTotal": 17457152,
            "heapUsed": 9992920,
            "external": 2370022,
            "arrayBuffers": 465430
          },
          "delta": "1338387808900"
        },
        {
          "allocated": {
            "rss": 46133248,
            "heapTotal": 17457152,
            "heapUsed": 9994704,
            "external": 2370022,
            "arrayBuffers": 465430
          },
          "delta": "1338387919000"
        },
        {
          "allocated": {
            "rss": 46133248,
            "heapTotal": 17457152,
            "heapUsed": 9996288,
            "external": 2370022,
            "arrayBuffers": 465430
          },
          "delta": "1338388029600"
        },
        {
          "allocated": {
            "rss": 46161920,
            "heapTotal": 17457152,
            "heapUsed": 10009360,
            "external": 2370022,
            "arrayBuffers": 465430
          },
          "delta": "1338389744000"
        }
      ]
    },
    {
      "start": "1338550403500",
      "end": "1338572776400",
      "memory": [
        {
          "allocated": {
            "rss": 43388928,
            "heapTotal": 11689984,
            "heapUsed": 8539064,
            "external": 2370722,
            "arrayBuffers": 465430
          },
          "delta": "1338550557000"
        },
        {
          "allocated": {
            "rss": 45916160,
            "heapTotal": 17457152,
            "heapUsed": 9968272,
            "external": 2370022,
            "arrayBuffers": 465430
          },
          "delta": "1338568153000"
        },
        {
          "allocated": {
            "rss": 46022656,
            "heapTotal": 17457152,
            "heapUsed": 9994584,
            "external": 2370022,
            "arrayBuffers": 465430
          },
          "delta": "1338569869200"
        },
        {
          "allocated": {
            "rss": 46030848,
            "heapTotal": 17457152,
            "heapUsed": 9999128,
            "external": 2370022,
            "arrayBuffers": 465430
          },
          "delta": "1338570146900"
        },
        {
          "allocated": {
            "rss": 46034944,
            "heapTotal": 17457152,
            "heapUsed": 10000952,
            "external": 2370022,
            "arrayBuffers": 465430
          },
          "delta": "1338570242000"
        },
        {
          "allocated": {
            "rss": 46051328,
            "heapTotal": 17457152,
            "heapUsed": 10007648,
            "external": 2370022,
            "arrayBuffers": 465430
          },
          "delta": "1338570837400"
        },
        {
          "allocated": {
            "rss": 46051328,
            "heapTotal": 17457152,
            "heapUsed": 10009432,
            "external": 2370022,
            "arrayBuffers": 465430
          },
          "delta": "1338570947300"
        },
        {
          "allocated": {
            "rss": 46055424,
            "heapTotal": 17457152,
            "heapUsed": 10011016,
            "external": 2370022,
            "arrayBuffers": 465430
          },
          "delta": "1338571062300"
        },
        {
          "allocated": {
            "rss": 46084096,
            "heapTotal": 17457152,
            "heapUsed": 10024088,
            "external": 2370022,
            "arrayBuffers": 465430
          },
          "delta": "1338572770800"
        }
      ]
    },
    {
      "start": "1338731740600",
      "end": "1338754158300",
      "memory": [
        {
          "allocated": {
            "rss": 43249664,
            "heapTotal": 11165696,
            "heapUsed": 8527048,
            "external": 2377502,
            "arrayBuffers": 465430
          },
          "delta": "1338731909900"
        },
        {
          "allocated": {
            "rss": 45682688,
            "heapTotal": 17457152,
            "heapUsed": 9913616,
            "external": 2370022,
            "arrayBuffers": 465430
          },
          "delta": "1338749494900"
        },
        {
          "allocated": {
            "rss": 45789184,
            "heapTotal": 17457152,
            "heapUsed": 9939928,
            "external": 2370022,
            "arrayBuffers": 465430
          },
          "delta": "1338751204700"
        },
        {
          "allocated": {
            "rss": 45797376,
            "heapTotal": 17457152,
            "heapUsed": 9944472,
            "external": 2370022,
            "arrayBuffers": 465430
          },
          "delta": "1338751485600"
        },
        {
          "allocated": {
            "rss": 45801472,
            "heapTotal": 17457152,
            "heapUsed": 9946296,
            "external": 2370022,
            "arrayBuffers": 465430
          },
          "delta": "1338751582100"
        },
        {
          "allocated": {
            "rss": 45817856,
            "heapTotal": 17457152,
            "heapUsed": 9952992,
            "external": 2370022,
            "arrayBuffers": 465430
          },
          "delta": "1338752178300"
        },
        {
          "allocated": {
            "rss": 45817856,
            "heapTotal": 17457152,
            "heapUsed": 9954776,
            "external": 2370022,
            "arrayBuffers": 465430
          },
          "delta": "1338752288200"
        },
        {
          "allocated": {
            "rss": 45821952,
            "heapTotal": 17457152,
            "heapUsed": 9956360,
            "external": 2370022,
            "arrayBuffers": 465430
          },
          "delta": "1338752404900"
        },
        {
          "allocated": {
            "rss": 45850624,
            "heapTotal": 17457152,
            "heapUsed": 9969432,
            "external": 2370022,
            "arrayBuffers": 465430
          },
          "delta": "1338754152200"
        }
      ]
    },
    {
      "start": "1338912359900",
      "end": "1338934617400",
      "memory": [
        {
          "allocated": {
            "rss": 44056576,
            "heapTotal": 11689984,
            "heapUsed": 8462216,
            "external": 2370722,
            "arrayBuffers": 465430
          },
          "delta": "1338912512500"
        },
        {
          "allocated": {
            "rss": 46252032,
            "heapTotal": 17457152,
            "heapUsed": 10016104,
            "external": 2370022,
            "arrayBuffers": 465430
          },
          "delta": "1338929939300"
        },
        {
          "allocated": {
            "rss": 46358528,
            "heapTotal": 17457152,
            "heapUsed": 10042416,
            "external": 2370022,
            "arrayBuffers": 465430
          },
          "delta": "1338931660300"
        },
        {
          "allocated": {
            "rss": 46366720,
            "heapTotal": 17457152,
            "heapUsed": 10046960,
            "external": 2370022,
            "arrayBuffers": 465430
          },
          "delta": "1338931945100"
        },
        {
          "allocated": {
            "rss": 46370816,
            "heapTotal": 17457152,
            "heapUsed": 10048784,
            "external": 2370022,
            "arrayBuffers": 465430
          },
          "delta": "1338932039400"
        },
        {
          "allocated": {
            "rss": 46383104,
            "heapTotal": 17457152,
            "heapUsed": 10055480,
            "external": 2370022,
            "arrayBuffers": 465430
          },
          "delta": "1338932645500"
        },
        {
          "allocated": {
            "rss": 46387200,
            "heapTotal": 17457152,
            "heapUsed": 10057264,
            "external": 2370022,
            "arrayBuffers": 465430
          },
          "delta": "1338932756900"
        },
        {
          "allocated": {
            "rss": 46391296,
            "heapTotal": 17457152,
            "heapUsed": 10058848,
            "external": 2370022,
            "arrayBuffers": 465430
          },
          "delta": "1338932873300"
        },
        {
          "allocated": {
            "rss": 46415872,
            "heapTotal": 17457152,
            "heapUsed": 10071920,
            "external": 2370022,
            "arrayBuffers": 465430
          },
          "delta": "1338934611000"
        }
      ]
    },
    {
      "start": "1339094399200",
      "end": "1339116520700",
      "memory": [
        {
          "allocated": {
            "rss": 43577344,
            "heapTotal": 11427840,
            "heapUsed": 8451920,
            "external": 2338103,
            "arrayBuffers": 426031
          },
          "delta": "1339094548800"
        },
        {
          "allocated": {
            "rss": 45957120,
            "heapTotal": 16932864,
            "heapUsed": 9830240,
            "external": 2330623,
            "arrayBuffers": 426031
          },
          "delta": "1339111925600"
        },
        {
          "allocated": {
            "rss": 46067712,
            "heapTotal": 16932864,
            "heapUsed": 9858960,
            "external": 2330623,
            "arrayBuffers": 426031
          },
          "delta": "1339113630500"
        },
        {
          "allocated": {
            "rss": 46071808,
            "heapTotal": 16932864,
            "heapUsed": 9969616,
            "external": 2330623,
            "arrayBuffers": 426031
          },
          "delta": "1339113907000"
        },
        {
          "allocated": {
            "rss": 46075904,
            "heapTotal": 16932864,
            "heapUsed": 9971440,
            "external": 2330623,
            "arrayBuffers": 426031
          },
          "delta": "1339114003700"
        },
        {
          "allocated": {
            "rss": 46088192,
            "heapTotal": 16932864,
            "heapUsed": 9978136,
            "external": 2330623,
            "arrayBuffers": 426031
          },
          "delta": "1339114588100"
        },
        {
          "allocated": {
            "rss": 46092288,
            "heapTotal": 16932864,
            "heapUsed": 9979920,
            "external": 2330623,
            "arrayBuffers": 426031
          },
          "delta": "1339114699900"
        },
        {
          "allocated": {
            "rss": 46096384,
            "heapTotal": 16932864,
            "heapUsed": 9981504,
            "external": 2330623,
            "arrayBuffers": 426031
          },
          "delta": "1339114810900"
        },
        {
          "allocated": {
            "rss": 46125056,
            "heapTotal": 16932864,
            "heapUsed": 9994576,
            "external": 2330623,
            "arrayBuffers": 426031
          },
          "delta": "1339116513600"
        }
      ]
    },
    {
      "start": "1339276431300",
      "end": "1339300286800",
      "memory": [
        {
          "allocated": {
            "rss": 43417600,
            "heapTotal": 11427840,
            "heapUsed": 8529416,
            "external": 2370722,
            "arrayBuffers": 465430
          },
          "delta": "1339276591100"
        },
        {
          "allocated": {
            "rss": 46006272,
            "heapTotal": 16932864,
            "heapUsed": 9809752,
            "external": 2370022,
            "arrayBuffers": 465430
          },
          "delta": "1339295384800"
        },
        {
          "allocated": {
            "rss": 46112768,
            "heapTotal": 16932864,
            "heapUsed": 9836064,
            "external": 2370022,
            "arrayBuffers": 465430
          },
          "delta": "1339297126000"
        },
        {
          "allocated": {
            "rss": 46120960,
            "heapTotal": 16932864,
            "heapUsed": 9840608,
            "external": 2370022,
            "arrayBuffers": 465430
          },
          "delta": "1339297406600"
        },
        {
          "allocated": {
            "rss": 46125056,
            "heapTotal": 16932864,
            "heapUsed": 9842432,
            "external": 2370022,
            "arrayBuffers": 465430
          },
          "delta": "1339297504300"
        },
        {
          "allocated": {
            "rss": 46137344,
            "heapTotal": 16932864,
            "heapUsed": 9849128,
            "external": 2370022,
            "arrayBuffers": 465430
          },
          "delta": "1339298102300"
        },
        {
          "allocated": {
            "rss": 46145536,
            "heapTotal": 17195008,
            "heapUsed": 10109448,
            "external": 2370022,
            "arrayBuffers": 465430
          },
          "delta": "1339298242400"
        },
        {
          "allocated": {
            "rss": 46149632,
            "heapTotal": 17195008,
            "heapUsed": 10111032,
            "external": 2370022,
            "arrayBuffers": 465430
          },
          "delta": "1339298367400"
        },
        {
          "allocated": {
            "rss": 46174208,
            "heapTotal": 17195008,
            "heapUsed": 10124104,
            "external": 2370022,
            "arrayBuffers": 465430
          },
          "delta": "1339300276600"
        }
      ]
    },
    {
      "start": "1339462045900",
      "end": "1339485356900",
      "memory": [
        {
          "allocated": {
            "rss": 43532288,
            "heapTotal": 11427840,
            "heapUsed": 8409840,
            "external": 2377702,
            "arrayBuffers": 465430
          },
          "delta": "1339462203900"
        },
        {
          "allocated": {
            "rss": 45899776,
            "heapTotal": 17195008,
            "heapUsed": 9817712,
            "external": 2370022,
            "arrayBuffers": 465430
          },
          "delta": "1339480463400"
        },
        {
          "allocated": {
            "rss": 46010368,
            "heapTotal": 17195008,
            "heapUsed": 9844056,
            "external": 2370022,
            "arrayBuffers": 465430
          },
          "delta": "1339482269800"
        },
        {
          "allocated": {
            "rss": 46018560,
            "heapTotal": 17195008,
            "heapUsed": 9848600,
            "external": 2370022,
            "arrayBuffers": 465430
          },
          "delta": "1339482548600"
        },
        {
          "allocated": {
            "rss": 46022656,
            "heapTotal": 17195008,
            "heapUsed": 9850424,
            "external": 2370022,
            "arrayBuffers": 465430
          },
          "delta": "1339482649900"
        },
        {
          "allocated": {
            "rss": 46034944,
            "heapTotal": 17195008,
            "heapUsed": 9989040,
            "external": 2370022,
            "arrayBuffers": 465430
          },
          "delta": "1339483262700"
        },
        {
          "allocated": {
            "rss": 46039040,
            "heapTotal": 17195008,
            "heapUsed": 9990824,
            "external": 2370022,
            "arrayBuffers": 465430
          },
          "delta": "1339483384000"
        },
        {
          "allocated": {
            "rss": 46043136,
            "heapTotal": 17195008,
            "heapUsed": 9992408,
            "external": 2370022,
            "arrayBuffers": 465430
          },
          "delta": "1339483495100"
        },
        {
          "allocated": {
            "rss": 46067712,
            "heapTotal": 17195008,
            "heapUsed": 10005480,
            "external": 2370022,
            "arrayBuffers": 465430
          },
          "delta": "1339485347200"
        }
      ]
    },
    {
      "start": "1339645237500",
      "end": "1339668233400",
      "memory": [
        {
          "allocated": {
            "rss": 43495424,
            "heapTotal": 11427840,
            "heapUsed": 8454952,
            "external": 2338103,
            "arrayBuffers": 426031
          },
          "delta": "1339645891200"
        },
        {
          "allocated": {
            "rss": 45842432,
            "heapTotal": 17195008,
            "heapUsed": 9875640,
            "external": 2330623,
            "arrayBuffers": 426031
          },
          "delta": "1339663617000"
        },
        {
          "allocated": {
            "rss": 45936640,
            "heapTotal": 17195008,
            "heapUsed": 9901952,
            "external": 2330623,
            "arrayBuffers": 426031
          },
          "delta": "1339665316000"
        },
        {
          "allocated": {
            "rss": 45948928,
            "heapTotal": 17195008,
            "heapUsed": 9906496,
            "external": 2330623,
            "arrayBuffers": 426031
          },
          "delta": "1339665590000"
        },
        {
          "allocated": {
            "rss": 45953024,
            "heapTotal": 17195008,
            "heapUsed": 9908320,
            "external": 2330623,
            "arrayBuffers": 426031
          },
          "delta": "1339665683700"
        },
        {
          "allocated": {
            "rss": 45965312,
            "heapTotal": 17195008,
            "heapUsed": 9915016,
            "external": 2330623,
            "arrayBuffers": 426031
          },
          "delta": "1339666269400"
        },
        {
          "allocated": {
            "rss": 45969408,
            "heapTotal": 17195008,
            "heapUsed": 9916800,
            "external": 2330623,
            "arrayBuffers": 426031
          },
          "delta": "1339666384300"
        },
        {
          "allocated": {
            "rss": 45973504,
            "heapTotal": 17195008,
            "heapUsed": 9918384,
            "external": 2330623,
            "arrayBuffers": 426031
          },
          "delta": "1339666494000"
        },
        {
          "allocated": {
            "rss": 45998080,
            "heapTotal": 17195008,
            "heapUsed": 9931456,
            "external": 2330623,
            "arrayBuffers": 426031
          },
          "delta": "1339668225200"
        }
      ]
    },
    {
      "start": "1339826219100",
      "end": "1339848123100",
      "memory": [
        {
          "allocated": {
            "rss": 43499520,
            "heapTotal": 11427840,
            "heapUsed": 8638424,
            "external": 2379986,
            "arrayBuffers": 467914
          },
          "delta": "1339826378800"
        },
        {
          "allocated": {
            "rss": 45862912,
            "heapTotal": 17457152,
            "heapUsed": 10082904,
            "external": 2372506,
            "arrayBuffers": 467914
          },
          "delta": "1339843518500"
        },
        {
          "allocated": {
            "rss": 45965312,
            "heapTotal": 17457152,
            "heapUsed": 10109216,
            "external": 2372506,
            "arrayBuffers": 467914
          },
          "delta": "1339845232200"
        },
        {
          "allocated": {
            "rss": 45973504,
            "heapTotal": 17457152,
            "heapUsed": 10113760,
            "external": 2372506,
            "arrayBuffers": 467914
          },
          "delta": "1339845514500"
        },
        {
          "allocated": {
            "rss": 45973504,
            "heapTotal": 17457152,
            "heapUsed": 10115584,
            "external": 2372506,
            "arrayBuffers": 467914
          },
          "delta": "1339845606900"
        },
        {
          "allocated": {
            "rss": 45989888,
            "heapTotal": 17457152,
            "heapUsed": 10122280,
            "external": 2372506,
            "arrayBuffers": 467914
          },
          "delta": "1339846196700"
        },
        {
          "allocated": {
            "rss": 45993984,
            "heapTotal": 17457152,
            "heapUsed": 10124064,
            "external": 2372506,
            "arrayBuffers": 467914
          },
          "delta": "1339846308100"
        },
        {
          "allocated": {
            "rss": 45993984,
            "heapTotal": 17457152,
            "heapUsed": 10125648,
            "external": 2372506,
            "arrayBuffers": 467914
          },
          "delta": "1339846421100"
        },
        {
          "allocated": {
            "rss": 46022656,
            "heapTotal": 17457152,
            "heapUsed": 10138720,
            "external": 2372506,
            "arrayBuffers": 467914
          },
          "delta": "1339848117300"
        }
      ]
    }
  ]
}
